stl2step/__init__.py
stl2step/__main__.py
stl2step/_version.py
stl2step-0.1.2.dist-info/LICENSE
stl2step-0.1.2.dist-info/LICENSES/AGPL-3.0-or-later.txt
stl2step-0.1.2.dist-info/LICENSES/CC-BY-4.0.txt
stl2step-0.1.2.dist-info/LICENSES/CC0-1.0.txt
stl2step-0.1.2.dist-info/METADATA
stl2step-0.1.2.dist-info/WHEEL
stl2step-0.1.2.dist-info/RECORD
