Metadata-Version: 2.3
Name: stl2step
Version: 0.1.2
Summary: Non-trivial conversion of STL files into STEP files.
License: AGPLv3
Author: Stefan Helmert
Author-email: stefan@entroserv.de
Requires-Python: >=3.9,<4.0
Classifier: License :: Other/Proprietary License
Classifier: Programming Language :: Python :: 3
Classifier: Programming Language :: Python :: 3.9
Classifier: Programming Language :: Python :: 3.10
Classifier: Programming Language :: Python :: 3.11
Classifier: Programming Language :: Python :: 3.12
Classifier: Programming Language :: Python :: 3.13
Requires-Dist: cadquery (>=2.4.0,<3.0.0)
Requires-Dist: numpy (>=1.23.5,<2.0.0)
Requires-Dist: numpy-stl (>=3.1.1,<4.0.0)
